<additionals>
    <tlLogic id="00" type="static" programID="0" offset="0">
        <phase duration="30" state="gGGgrrgrrgrr"/>
        <phase duration="30" state="grrgGGgrrgrr"/>
        <phase duration="30" state="grrgrrgGGgrr"/>
        <phase duration="30" state="grrgrrgrrgGG"/>
    </tlLogic>
    <tlLogic id="01" type="static" programID="0" offset="0">
        <phase duration="30" state="gGGgrrgrrgrr"/>
        <phase duration="30" state="grrgGGgrrgrr"/>
        <phase duration="30" state="grrgrrgGGgrr"/>
        <phase duration="30" state="grrgrrgrrgGG"/>
    </tlLogic>
    <tlLogic id="02" type="static" programID="0" offset="0">
        <phase duration="30" state="gGGgrrgrrgrr"/>
        <phase duration="30" state="grrgGGgrrgrr"/>
        <phase duration="30" state="grrgrrgGGgrr"/>
        <phase duration="30" state="grrgrrgrrgGG"/>
    </tlLogic>
    <tlLogic id="03" type="static" programID="0" offset="0">
        <phase duration="30" state="gGGgrrgrrgrr"/>
        <phase duration="30" state="grrgGGgrrgrr"/>
        <phase duration="30" state="grrgrrgGGgrr"/>
        <phase duration="30" state="grrgrrgrrgGG"/>
    </tlLogic>
    <tlLogic id="04" type="static" programID="0" offset="0">
        <phase duration="30" state="gGGgrrgrrgrr"/>
        <phase duration="30" state="grrgGGgrrgrr"/>
        <phase duration="30" state="grrgrrgGGgrr"/>
        <phase duration="30" state="grrgrrgrrgGG"/>
    </tlLogic>
    <tlLogic id="05" type="static" programID="0" offset="0">
        <phase duration="30" state="gGGgrrgrrgrr"/>
        <phase duration="30" state="grrgGGgrrgrr"/>
        <phase duration="30" state="grrgrrgGGgrr"/>
        <phase duration="30" state="grrgrrgrrgGG"/>
    </tlLogic>
    <tlLogic id="06" type="static" programID="0" offset="0">
        <phase duration="30" state="gGGgrrgrrgrr"/>
        <phase duration="30" state="grrgGGgrrgrr"/>
        <phase duration="30" state="grrgrrgGGgrr"/>
        <phase duration="30" state="grrgrrgrrgGG"/>
    </tlLogic>
    <tlLogic id="07" type="static" programID="0" offset="0">
        <phase duration="30" state="gGGgrrgrrgrr"/>
        <phase duration="30" state="grrgGGgrrgrr"/>
        <phase duration="30" state="grrgrrgGGgrr"/>
        <phase duration="30" state="grrgrrgrrgGG"/>
    </tlLogic>
    <tlLogic id="08" type="static" programID="0" offset="0">
        <phase duration="30" state="gGGgrrgrrgrr"/>
        <phase duration="30" state="grrgGGgrrgrr"/>
        <phase duration="30" state="grrgrrgGGgrr"/>
        <phase duration="30" state="grrgrrgrrgGG"/>
    </tlLogic>

</additionals>
